wizagent/__init__.py
wizagent/wizagent.py
wizagent/deep_research/__init__.py
wizagent/deep_research/agent.py
wizagent/deep_research/prompts.py
wizagent/deep_research/schemas.py
wizagent/deep_research/state.py
wizagent/gems/__init__.py
wizagent/gems/gem_parser.py
wizagent/search/__init__.py
wizagent/search/agent.py
wizagent/search/state.py
wizagent-0.0.2.dist-info/licenses/LICENSE
wizagent-0.0.2.dist-info/METADATA
wizagent-0.0.2.dist-info/WHEEL
wizagent-0.0.2.dist-info/top_level.txt
wizagent-0.0.2.dist-info/RECORD
